maverick/__init__.py
maverick/__main__.py
maverick/_version.py
maverick/combine_bin_cli.py
maverick/config.json
maverick/event_hander.py
maverick/initialization.py
maverick/maverick.py
maverick/maverick_combine_and_bin_cli.py
maverick/bin/__init__.py
maverick/bin/auto_event_handler.py
maverick/bin/event_hander.py
maverick/bin/linear_bin.py
maverick/bin/log_bin.py
maverick/bin/manual_event_handler.py
maverick/bin/manual_right_click.py
maverick/bin/plot.py
maverick/bin/preview_full_bin_axis.py
maverick/bin/settings.py
maverick/bin/statistics.py
maverick/combine/__init__.py
maverick/combine/combine.py
maverick/combine/event_handler.py
maverick/export/__init__.py
maverick/export/export_bin_table.py
maverick/export/export_images.py
maverick/export/utilities.py
maverick/icons/auto.png
maverick/icons/bin.png
maverick/icons/combine.png
maverick/icons/manual.png
maverick/icons/more_infos.png
maverick/icons/plotSettings.png
maverick/icons/refresh.png
maverick/icons/stats_plot.png
maverick/icons/stats_table.png
maverick/load/__init__.py
maverick/load/load_bin_table.py
maverick/load/load_files.py
maverick/log/__init__.py
maverick/log/log_launcher.py
maverick/session/__init__.py
maverick/session/load_previous_session_launcher.py
maverick/session/session_handler.py
maverick/ui/__init__.py
maverick/ui/log.ui
maverick/ui/log_settings.ui
maverick/ui/mainWindow.ui
maverick/ui/ui_bin_settings.ui
maverick/ui/ui_load_previous_session.ui
maverick/ui/ui_preview_full_bin_axis.ui
maverick/ui/ui_time_spectra_preview.ui
maverick/utilities/__init__.py
maverick/utilities/check.py
maverick/utilities/config_handler.py
maverick/utilities/file_handler.py
maverick/utilities/get.py
maverick/utilities/image_handler.py
maverick/utilities/math_tools.py
maverick/utilities/matplotlibview.py
maverick/utilities/status_message_config.py
maverick/utilities/string.py
maverick/utilities/table_handler.py
maverick/utilities/time_spectra.py
maverick/utilities/widgets_handler.py
imaverick-0.0.7.3.dist-info/METADATA
imaverick-0.0.7.3.dist-info/WHEEL
imaverick-0.0.7.3.dist-info/top_level.txt
imaverick-0.0.7.3.dist-info/RECORD
