Metadata-Version: 2.1
Name: imaverick
Version: 0.0.7.3
Home-page: http://github.com/ornlneutronimaging/maverick
Author: Jean Bilheux
Author-email: Jean <j35@ornl.gov>
Project-URL: Homepage, https://github.com/ornlneutronimaging/maverick
Project-URL: Bug Tracker, https://github.com/ornlneutronimaging/maverick
Classifier: Programming Language :: Python :: 3
Classifier: License :: OSI Approved :: MIT License
Classifier: Operating System :: OS Independent
Requires-Python: >=3.7
Requires-Dist: args
Requires-Dist: astropy
Requires-Dist: configparser
Requires-Dist: numpy
Requires-Dist: pandas
Requires-Dist: Pillow
Requires-Dist: progressbar2
Requires-Dist: pyqtgraph (==0.12.1)
Requires-Dist: scikit-image
Requires-Dist: scipy
Requires-Dist: neutronbraggedge
Requires-Dist: qtpy
Requires-Dist: inflect
Requires-Dist: matplotlib
Requires-Dist: NeuNorm
Requires-Dist: tomli
Requires-Dist: tqdm
